ai_escalator.py
banner.py
cli.py
console.py
decision.py
diff_reader.py
exit_codes.py
git_utils.py
license.py
policy_engine.py
policy_loader.py
report.py
risk_engine.py
theme.py
version.py
rules/__init__.py
rules/cross_service.py
rules/def_reader.py
rules/git_utils.py
rules/infra_changes.py
rules/large_diffs.py
rules/sensitive_files.py
rules/test_coverage.py
sentra-0.1.0.dist-info/licenses/license.py
sentra-0.1.0.dist-info/METADATA
sentra-0.1.0.dist-info/WHEEL
sentra-0.1.0.dist-info/entry_points.txt
sentra-0.1.0.dist-info/top_level.txt
sentra-0.1.0.dist-info/RECORD
